digipin/__init__.py
digipin/cli.py
digipin/decoder.py
digipin/django_ext.py
digipin/encoder.py
digipin/fastapi_ext.py
digipin/flask_ext.py
digipin/neighbors.py
digipin/pandas_ext.py
digipin/polyfill.py
digipin/polyfill_quadtree.py
digipin/py.typed
digipin/utils.py
digipin/viz.py
digipinpy-1.7.0.dist-info/licenses/LICENSE
digipinpy-1.7.0.dist-info/METADATA
digipinpy-1.7.0.dist-info/WHEEL
digipinpy-1.7.0.dist-info/entry_points.txt
digipinpy-1.7.0.dist-info/top_level.txt
digipinpy-1.7.0.dist-info/RECORD
