Metadata-Version: 2.4
Name: digipinpy
Version: 1.7.0
Summary: Official Python implementation of DIGIPIN - India's national geocoding standard by Department of Posts
Author-email: SAMARTHA H V <samarthsmg14@gmail.com>
Maintainer-email: MR SHIVAKUMAR <hmrshivu@gmail.com>
License: MIT
Project-URL: Homepage, https://github.com/DEADSERPENT/digipin
Project-URL: Documentation, https://github.com/DEADSERPENT/digipin/blob/main/docs/index.md
Project-URL: Repository, https://github.com/DEADSERPENT/digipin
Project-URL: Issue Tracker, https://github.com/DEADSERPENT/digipin/issues
Project-URL: Source Code, https://github.com/DEADSERPENT/digipin
Project-URL: Changelog, https://github.com/DEADSERPENT/digipin/blob/main/CHANGELOG.md
Project-URL: Bug Reports, https://github.com/DEADSERPENT/digipin/issues/new?template=bug_report.md
Project-URL: Feature Requests, https://github.com/DEADSERPENT/digipin/issues/new?template=feature_request.md
Keywords: digipin,geocoding,geolocation,india,gis,addressing,postal,location,coordinates,government,department-of-posts
Classifier: Development Status :: 5 - Production/Stable
Classifier: Intended Audience :: Developers
Classifier: Intended Audience :: Science/Research
Classifier: Intended Audience :: Information Technology
Classifier: Natural Language :: English
Classifier: Operating System :: OS Independent
Classifier: Programming Language :: Python
Classifier: Programming Language :: Python :: 3
Classifier: Programming Language :: Python :: 3.7
Classifier: Programming Language :: Python :: 3.8
Classifier: Programming Language :: Python :: 3.9
Classifier: Programming Language :: Python :: 3.10
Classifier: Programming Language :: Python :: 3.11
Classifier: Programming Language :: Python :: 3.12
Classifier: Programming Language :: Python :: 3.13
Classifier: Programming Language :: Python :: Implementation :: CPython
Classifier: Programming Language :: Python :: Implementation :: PyPy
Classifier: Topic :: Scientific/Engineering :: GIS
Classifier: Topic :: Software Development :: Libraries :: Python Modules
Classifier: Topic :: Utilities
Classifier: Typing :: Typed
Requires-Python: >=3.7
License-File: LICENSE
Provides-Extra: dev
Requires-Dist: pytest>=7.0; extra == "dev"
Requires-Dist: pytest-cov>=4.0; extra == "dev"
Requires-Dist: black>=22.0; extra == "dev"
Requires-Dist: flake8>=5.0; extra == "dev"
Requires-Dist: mypy>=0.990; extra == "dev"
Provides-Extra: test
Requires-Dist: pytest>=7.0; extra == "test"
Requires-Dist: pytest-cov>=4.0; extra == "test"
Provides-Extra: pandas
Requires-Dist: pandas>=1.3.0; extra == "pandas"
Requires-Dist: numpy>=1.21.0; extra == "pandas"
Requires-Dist: tqdm>=4.62.0; extra == "pandas"
Requires-Dist: openpyxl>=3.0.0; extra == "pandas"
Provides-Extra: django
Requires-Dist: django>=3.2; extra == "django"
Provides-Extra: fastapi
Requires-Dist: fastapi>=0.68.0; extra == "fastapi"
Requires-Dist: pydantic>=1.8.0; extra == "fastapi"
Requires-Dist: uvicorn>=0.15.0; extra == "fastapi"
Provides-Extra: geo
Requires-Dist: shapely>=2.0.0; extra == "geo"
Provides-Extra: viz
Requires-Dist: folium>=0.12.0; extra == "viz"
Dynamic: license-file
